mtlibs/SSH.py
mtlibs/__init__.py
mtlibs/amplifyHelper.py
mtlibs/auth0_utils.py
mtlibs/cognito_util.py
mtlibs/config.py
mtlibs/container_config.py
mtlibs/docker_helper.py
mtlibs/frpcProc.py
mtlibs/fs.py
mtlibs/ghworker.py
mtlibs/github.py
mtlibs/json_encoder.py
mtlibs/jwt_helper.py
mtlibs/mtutils.py
mtlibs/nginx_helper copy.py
mtlibs/nginx_helper.py
mtlibs/oauthHelper.py
mtlibs/openvpnClientProc.py
mtlibs/openvpnProc.py
mtlibs/process_helper.py
mtlibs/proxyUtil.py
mtlibs/sshClient.py
mtlibs/tar_helper.py
mtlibs/testutils.py
mtlibs/tor_helper.py
mtlibs/yaml.py
mtlibs/aws/__init__.py
mtlibs/aws/ddb_helper.py
mtlibs/aws/s3_helper copy.py--
mtlibs/aws/s3_helper.py
mtlibs/aws/s3_imageresize.py
mtlibs/az/demo1222.py--
mtlibs/az/webdeploy.py--
mtlibs/az/webdeploy2.py--
mtlibs/cli/__init__.py
mtlibs/cli/dc.py
mtlibs/cli/dockerdev.py
mtlibs/cli/gitup.py
mtlibs/cli/mtbuild.py
mtlibs/cli/mtbundler.py
mtlibs/cli/mtdp.py
mtlibs/cli/mtgp.py
mtlibs/cli/mtngrok.py
mtlibs/cli/mtproxy.py--
mtlibs/cli/mtpub.py
mtlibs/cli/mtwpdev.py
mtlibs/cli/phpfpm.py
mtlibs/cli/sub_commands/__init__.py
mtlibs/cli/sub_commands/azure_rancher_group.py
mtlibs/cli/sub_commands/build.py
mtlibs/cli/sub_commands/default.py
mtlibs/cli/sub_commands/demoflask.py
mtlibs/cli/sub_commands/dev.py
mtlibs/cli/sub_commands/devserver.py
mtlibs/cli/sub_commands/port.py
mtlibs/cli/sub_commands/proxy.py
mtlibs/cli/sub_commands/simplehttp.py
mtlibs/cli/sub_commands/sshd.py
mtlibs/cli/sub_commands/version.py
mtlibs/data/mtxtun.yml
mtlibs/data/sshd.sh
mtlibs/data/tun.js
mtlibs/data/v2ray.config.json
mtlibs/data/clash/config copy.yaml
mtlibs/data/clash/config-tproxy copy.yml--
mtlibs/data/clash/config-tproxy.yml--
mtlibs/data/clash/config.yaml
mtlibs/data/clash/config_direct.yaml
mtlibs/data/clash/config_local.yaml
mtlibs/data/mitmproxy/command_history
mtlibs/data/mitmproxy/mitmproxy-ca-cert.cer
mtlibs/data/mitmproxy/mitmproxy-ca-cert.p12
mtlibs/data/mitmproxy/mitmproxy-ca-cert.pem
mtlibs/data/mitmproxy/mitmproxy-ca.p12
mtlibs-0.0.20230123035307.dist-info/entry_points.txt
mtlibs-0.0.20230123035307.dist-info/WHEEL
mtlibs-0.0.20230123035307.dist-info/METADATA
mtlibs-0.0.20230123035307.dist-info/RECORD
