Metadata-Version: 2.1
Name: mtlibs
Version: 0.0.20230123035307
Summary: A small example package
Author-email: Example Author <author@example.com>
Requires-Python: >=3.7
Classifier: Programming Language :: Python :: 3
Classifier: License :: OSI Approved :: MIT License
Classifier: Operating System :: OS Independent
Requires-Dist: ReportLab>=1.2 ; extra == "pdf"
Requires-Dist: RXP ; extra == "pdf"
Requires-Dist: docutils>=0.3 ; extra == "rest"
Requires-Dist: pack ==1.1, ==1.3 ; extra == "rest"
Project-URL: Bug Tracker, https://github.com/pypa/sampleproject/issues
Project-URL: Homepage, https://github.com/pypa/sampleproject
Provides-Extra: pdf
Provides-Extra: rest
